aas_cli/__init__.py
aas_cli/app.py
aas_cli/args.py
aas_cli/formats.py
aas_cli/handlers.py
aas_cli/opts.py
aas_cli/pretty.py
aas_cli/resolve.py
aas_cli/simplify.py
aas_cli/commands/__init__.py
aas_cli/commands/decode.py
aas_cli/commands/encode.py
aas_cli/commands/info.py
aas_cli/commands/nuke.py
aas_cli/commands/upload.py
aas_cli/commands/groups/__init__.py
aas_cli/commands/groups/create.py
aas_cli/commands/groups/delete.py
aas_cli/commands/groups/get.py
aas_cli/commands/groups/update.py
aas_cli-0.0.1.dist-info/METADATA
aas_cli-0.0.1.dist-info/WHEEL
aas_cli-0.0.1.dist-info/entry_points.txt
aas_cli-0.0.1.dist-info/licenses/LICENSE
aas_cli-0.0.1.dist-info/RECORD
