Metadata-Version: 2.4
Name: aas-cli
Version: 0.0.1
Summary: A Python Command-Line Interface (CLI) for Eclipse BaSyx to manage Asset Administration Shells (AAS)
Project-URL: Homepage, https://github.com/SmartFactory-KL/aas-cli
Project-URL: Issues, https://github.com/SmartFactory-KL/aas-cli/issues
Project-URL: Documentation, https://shellsmith.pages.dev/cli/
Author-email: Peter Stein <peter.stein@dfki.de>
License: MIT License
License-File: LICENSE
Keywords: aas,asset-administration-shell,basyx,cli,digital-twin,eclipse-basyx,i40,industry40,python,rest-client,typer
Classifier: License :: OSI Approved :: MIT License
Classifier: Operating System :: OS Independent
Classifier: Programming Language :: Python :: 3
Classifier: Programming Language :: Python :: 3.10
Classifier: Programming Language :: Python :: 3.11
Classifier: Programming Language :: Python :: 3.12
Classifier: Programming Language :: Python :: 3.13
Requires-Python: >=3.10
Requires-Dist: shellsmith>=0.4.0
Requires-Dist: typer
Provides-Extra: test
Requires-Dist: mypy; extra == 'test'
Requires-Dist: pytest; extra == 'test'
Requires-Dist: pytest-cov; extra == 'test'
Requires-Dist: ruff; extra == 'test'
